flask_transmute/__init__.py
flask_transmute/handler.py
flask_transmute/legacy.py
flask_transmute/route.py
flask_transmute/swagger.py
flask_transmute/tests/__init__.py
flask_transmute/tests/conftest.py
flask_transmute/tests/example.py
flask_transmute/tests/gunicorn_config.py
flask_transmute/tests/test_app.py
flask_transmute/tests/test_full.py
flask_transmute/tests/test_legacy_error.py
flask_transmute-1.4.0.dist-info/DESCRIPTION.rst
flask_transmute-1.4.0.dist-info/METADATA
flask_transmute-1.4.0.dist-info/RECORD
flask_transmute-1.4.0.dist-info/WHEEL
flask_transmute-1.4.0.dist-info/metadata.json
flask_transmute-1.4.0.dist-info/top_level.txt
