Metadata-Version: 2.0
Name: flask-transmute
Version: 1.4.0
Summary: a flask plugin to generate routes from objects.
Home-page: UNKNOWN
Author: Yusuke Tsutsumi
Author-email: yusuke@tsutsumi.io
License: UNKNOWN
Platform: UNKNOWN
Classifier: Development Status :: 3 - Alpha
Classifier: Operating System :: MacOS
Classifier: Operating System :: POSIX :: Linux
Classifier: Topic :: System :: Software Distribution
Classifier: License :: OSI Approved :: MIT License
Classifier: Programming Language :: Python
Classifier: Programming Language :: Python :: 2
Classifier: Programming Language :: Python :: 2.6
Classifier: Programming Language :: Python :: 2.7
Classifier: Programming Language :: Python :: 3
Classifier: Programming Language :: Python :: 3.2
Classifier: Programming Language :: Python :: 3.3
Classifier: Programming Language :: Python :: 3.4
Requires-Dist: Flask
Requires-Dist: transmute-core (>=0.4.6)
